cubedsphere/__init__.py
cubedsphere/const.py
cubedsphere/grid.py
cubedsphere/plot.py
cubedsphere/regrid.py
cubedsphere/utils.py
cubedsphere/exorad/__init__.py
cubedsphere/exorad/utils.py
cubedsphere-0.2.1.dist-info/LICENSE
cubedsphere-0.2.1.dist-info/METADATA
cubedsphere-0.2.1.dist-info/WHEEL
cubedsphere-0.2.1.dist-info/top_level.txt
cubedsphere-0.2.1.dist-info/RECORD
