Metadata-Version: 2.1
Name: cubedsphere
Version: 0.2.1
Summary: Library for post processing of MITgcm cubed sphere data
Home-page: https://github.com/AaronDavidSchneider/cubedsphere
Download-URL: https://github.com/AaronDavidSchneider/chemcomp/archive/0.1.3.zip
Author: Aaron David Schneider
Author-email: aaron.schneider@nbi.ku.dk
License: MIT
Classifier: Development Status :: 4 - Beta
Classifier: Intended Audience :: Developers
Classifier: Topic :: Software Development :: Build Tools
Classifier: License :: OSI Approved :: MIT License
Classifier: Programming Language :: Python :: 3.6
Classifier: Programming Language :: Python :: 3.7
Classifier: Programming Language :: Python :: 3.8
Classifier: Programming Language :: Python :: 3.9
License-File: LICENSE
Requires-Dist: numpy
Requires-Dist: matplotlib
Requires-Dist: xesmf >0.5.0
Requires-Dist: esmpy
Requires-Dist: xgcm ==0.5.2
Requires-Dist: xmitgcm >0.5.0
Requires-Dist: xarray
Requires-Dist: f90nml
